LICENSE
MANIFEST.in
README.md
setup.cfg
setup.py
comparison/__init__.py
comparison/config.py
comparison/defaults.py
comparison/middleware.py
comparison/service.py
comparison/settings.py
comparison/urls.py
comparison/views.py
comparison/locale/ru/LC_MESSAGES/django.mo
comparison/locale/ru/LC_MESSAGES/django.po
comparison/locale/uk/LC_MESSAGES/django.mo
comparison/locale/uk/LC_MESSAGES/django.po
comparison/static/comparison/comparison.js
comparison/templates/comparison/dropdown.html
comparison/templates/comparison/index.html
comparison/templates/comparison/toggle_button.html
comparison/templatetags/__init__.py
comparison/templatetags/comparison.py
django_mp_shop_comparison.egg-info/PKG-INFO
django_mp_shop_comparison.egg-info/SOURCES.txt
django_mp_shop_comparison.egg-info/dependency_links.txt
django_mp_shop_comparison.egg-info/top_level.txt