Metadata-Version: 1.1
Name: django-mp-shop-comparison
Version: 2.0
Summary: Django shop comparison app
Home-page: https://github.com/pmaigutyak/mp-shop-comparison
Author: Paul Maigutyak
Author-email: pmaigutyak@gmail.com
License: MIT
Download-URL: https://github.com/pmaigutyak/mp-shop-comparison/archive/2.0.tar.gz
Platform: UNKNOWN
